lib/__init__.py
lib/end_of_distribution.py
end_of_distribution-0.1.0.dist-info/LICENCE
end_of_distribution-0.1.0.dist-info/METADATA
end_of_distribution-0.1.0.dist-info/WHEEL
end_of_distribution-0.1.0.dist-info/top_level.txt
end_of_distribution-0.1.0.dist-info/RECORD
