Metadata-Version: 2.1
Name: end_of_distribution
Version: 0.1.0
Summary: A Python library for detecting outliers at the end of the distribution
Home-page: https://github.com/adityayadav0111/end_of_distribution
Author: Aditya Yadav
Author-email: aditya.yadav.bse@gmail.com
License: MIT
Classifier: Programming Language :: Python :: 3
Classifier: License :: OSI Approved :: MIT License
Classifier: Operating System :: OS Independent
Requires-Python: >=3.6
License-File: LICENCE
